sensai/__init__.py
sensai/util/__init__.py
sensai/util/aggregation.py
sensai/util/cache.py
sensai/util/cache_azure.py
sensai/util/cache_mysql.py
sensai/util/datastruct.py
sensai/util/deprecation.py
sensai/util/dtype.py
sensai/util/git.py
sensai/util/hash.py
sensai/util/helper.py
sensai/util/io.py
sensai/util/jscode.py
sensai/util/logging.py
sensai/util/math.py
sensai/util/multiprocessing.py
sensai/util/pandas.py
sensai/util/pickle.py
sensai/util/plot.py
sensai/util/profiling.py
sensai/util/sequences.py
sensai/util/string.py
sensai/util/tensorboard.py
sensai/util/test.py
sensai/util/time.py
sensai/util/typing.py
sensai/util/version.py
sensai_utils-1.6.0.dist-info/licenses/LICENSE
sensai_utils-1.6.0.dist-info/METADATA
sensai_utils-1.6.0.dist-info/WHEEL
sensai_utils-1.6.0.dist-info/top_level.txt
sensai_utils-1.6.0.dist-info/RECORD
